LICENSE
MANIFEST.in
README.rst
setup.py
django_addanother/__init__.py
django_addanother/views.py
django_addanother/widgets.py
django_addanother.egg-info/PKG-INFO
django_addanother.egg-info/SOURCES.txt
django_addanother.egg-info/dependency_links.txt
django_addanother.egg-info/not-zip-safe
django_addanother.egg-info/top_level.txt
django_addanother/contrib/__init__.py
django_addanother/contrib/select2.py
django_addanother/static/django_addanother/addanother.css
django_addanother/static/django_addanother/django_jquery.js
django_addanother/templates/django_addanother/related_widget_wrapper.html