Metadata-Version: 2.1
Name: django-addanother
Version: 2.1.0
Summary: "Add another" buttons outside the Django admin
Home-page: https://github.com/jonashaag/django-addanother
Author: Jonas Haag, James Pic
Author-email: jonas@lophus.org, jamespic@gmail.com
License: UNKNOWN
Platform: UNKNOWN
Classifier: Intended Audience :: Developers
Classifier: License :: OSI Approved :: ISC License (ISCL)
Classifier: Programming Language :: Python
Classifier: Programming Language :: Python :: 2.7
Classifier: Programming Language :: Python :: 3.5
Classifier: Programming Language :: Python :: 3.6
Classifier: Programming Language :: Python :: 3.7
Classifier: Programming Language :: Python :: 3.8
Classifier: Programming Language :: Python :: 3.9
Classifier: Programming Language :: Python :: 3.10
License-File: LICENSE
